{
	"class" : {
		"open" : "SeanDeNigris 7/25/2012 10:45",
		"spec" : "SeanDeNigris 8/27/2012 16:09",
		"title" : "SeanDeNigris 7/25/2012 09:39" },
	"instance" : {
		"browse:" : "MarcusDenker 11/30/2012 11:08",
		"browseButton" : "SeanDeNigris 7/25/2012 10:29",
		"debugButton" : "SeanDeNigris 7/25/2012 09:41",
		"errorListModel" : "SeanDeNigris 7/25/2012 09:44",
		"imageVersion" : "BenjaminVanRyseghem 8/27/2012 14:56",
		"imageVersionLabel" : "BenjaminVanRyseghem 8/27/2012 14:56",
		"initialExtent" : "SeanDeNigris 7/25/2012 10:46",
		"initializePresenter" : "MarianoMartinezPeck 8/28/2012 14:10",
		"initializeWidgets" : "MarianoMartinezPeck 8/28/2012 13:43",
		"materialize:" : "MarianoMartinezPeck 8/30/2012 06:35",
		"selectTestFailures" : "MarianoMartinezPeck 8/28/2012 14:00",
		"timeStamp" : "BenjaminVanRyseghem 8/27/2012 14:56",
		"timeStampLabel" : "BenjaminVanRyseghem 8/27/2012 14:56",
		"vmVersion" : "SeanDeNigris 8/27/2012 14:00",
		"vmVersionLabel" : "SeanDeNigris 8/27/2012 13:59" } }
