{
	"class" : {
		"buildRefactoringMethodShortcutsOn:" : "BenjaminVanRyseghem 6/24/2012 22:29",
		"buildRefactoringShortcutsOn:" : "BenjaminVanRyseghem 6/27/2012 13:27",
		"buildSourceCodeShortcutsOn:" : "BenjaminVanRyseghem 9/14/2012 14:58",
		"classRefactoringSubmenu:" : "BenjaminVanRyseghem 7/13/2012 16:07",
		"classVarRefactoringSubmenu:" : "BenjaminVanRyseghem 5/13/2012 17:56",
		"codeRewritingClassSubmenu:" : "BenjaminVanRyseghem 5/13/2012 17:54",
		"instVarRefactoringSubmenu:" : "BenjaminVanRyseghem 5/13/2012 17:57",
		"methodRefactoringSubMenu:" : "BenjaminVanRyseghem 5/13/2012 17:59",
		"model:" : "",
		"promptOnRefactoring" : "",
		"refactoringClassMenu:" : "BenjaminVanRyseghem 5/13/2012 17:53",
		"refactoringMethodMenu:" : "BenjaminVanRyseghem 6/28/2012 15:13",
		"sourceCodeRefactoringMenu:" : "",
		"sourceCodeRefactoringMenuHolder:" : "BenjaminVanRyseghem 9/14/2012 15:00" },
	"instance" : {
		"abstractClassVarFrom:" : "",
		"abstractInstVarFrom:" : "",
		"accessorsClassVarFrom:" : "",
		"accessorsInstVarFrom:" : "",
		"addAParameterFor:" : "",
		"addClassVarFrom:" : "",
		"addInstVarFrom:" : "",
		"buildRenameRefactoringEngineFor:" : "",
		"categoryRegex" : "",
		"categoryRegexText" : "",
		"changeManager" : "",
		"changeSuperclassOf:" : "BenjaminVanRyseghem 4/18/2012 17:11",
		"chooseFrom:title:lines:" : "",
		"chooseMultipleFrom:" : "",
		"chooseMultipleFrom:title:" : "",
		"class:andClassVariable:" : "",
		"class:andInstVariable:" : "",
		"classObjectFor:" : "",
		"classRegex" : "",
		"classRegexText" : "",
		"createCascadeBetween:from:" : "",
		"extractBetween:from:" : "",
		"extractToComponentBetween:from:" : "",
		"extractToMethodTextSelection" : "BenjaminVanRyseghem 4/18/2012 17:45",
		"extractToTempTextSelection" : "BenjaminVanRyseghem 4/18/2012 17:44",
		"extractToTemporaryBetween:from:" : "",
		"formatSourceCode" : "BenjaminVanRyseghem 9/14/2012 14:57",
		"generateAccessors" : "",
		"generateSubclass" : "BenjaminVanRyseghem 7/13/2012 16:09",
		"generateSuperClass" : "BenjaminVanRyseghem 7/13/2012 16:09",
		"handleError:" : "",
		"handleMethodNameRequest:" : "",
		"handleWarning:" : "",
		"inlineAllSendersFor:" : "",
		"inlineMethodBetween:from:" : "",
		"inlineMethodFromComponentBetween:from:" : "",
		"inlineParameterFor:" : "",
		"inlineTemporaryBetween:from:" : "",
		"internalPerformRefactorings:" : "",
		"model" : "",
		"model:" : "",
		"moveMethodFor:" : "",
		"moveVariableDefinitionBetween:from:" : "",
		"openEnvironment:for:" : "",
		"performRefactoring:" : "",
		"performRefactorings:" : "",
		"privateAbstractClassVarFrom:" : "",
		"privateAbstractInstVarFrom:" : "",
		"privateAccessorsClassVarFrom:" : "",
		"privateAccessorsInstVarFrom:" : "",
		"privateAddAParameterFor:" : "BenjaminVanRyseghem 3/26/2012 17:46",
		"privateAddClassVarFrom:" : "",
		"privateAddInstVarFrom:" : "",
		"privateCreateCascadeBetween:from:" : "",
		"privateExtractBetween:from:" : "",
		"privateExtractToComponentBetween:from:" : "",
		"privateExtractToTemporaryBetween:from:" : "",
		"privateGenerateAccessorsFor:" : "",
		"privateGenerateSubclassFor:" : "",
		"privateGenerateSuperClassFor:" : "",
		"privateInlineAllSendersFor:" : "",
		"privateInlineMethodBetween:from:" : "",
		"privateInlineMethodFromComponentBetween:from:" : "",
		"privateInlineParameterFor:" : "",
		"privateInlineTemporaryBetween:from:" : "",
		"privateMoveMethodFor:" : "",
		"privateMoveVariableDefinitionBetween:from:" : "",
		"privatePullUpClassVarFrom:" : "",
		"privatePullUpInstVarFrom:" : "",
		"privatePullUpMethodsFor:" : "",
		"privatePushDownClassVarFrom:" : "",
		"privatePushDownInstVarFrom:" : "",
		"privatePushDownMethodsFor:" : "",
		"privateRealizeClassFor:" : "",
		"privateRemoveClassVarFrom:" : "",
		"privateRemoveClassesFor:" : "",
		"privateRemoveInstVarFrom:" : "",
		"privateRemoveMethodsFor:" : "",
		"privateRemoveParameterMethodFor:" : "BenjaminVanRyseghem 3/26/2012 17:49",
		"privateRenameClassVarFrom:" : "BenjaminVanRyseghem 4/18/2012 16:58",
		"privateRenameClassVarNamed:from:" : "BenjaminVanRyseghem 4/18/2012 16:58",
		"privateRenameInstVarFrom:" : "BenjaminVanRyseghem 4/18/2012 16:57",
		"privateRenameInstVarNamed:from:" : "BenjaminVanRyseghem 4/18/2012 16:57",
		"privateRenameMethodFor:" : "",
		"privateRenameTemporaryNamed:Between:from:" : "",
		"privateSplitCascadeBetween:from:" : "",
		"privateSplitClassFor:" : "",
		"privateSwapMethodFor:" : "",
		"privateTemporaryToInstanceVariableNamed:Between:from:" : "",
		"promptOnRefactoring" : "",
		"protocolRegex" : "",
		"protocolRegexText" : "",
		"pullUpClassVarFrom:" : "",
		"pullUpInstVarFrom:" : "",
		"pullUpMethodsFor:" : "",
		"pushDownClassVarFrom:" : "",
		"pushDownInstVarFrom:" : "",
		"pushDownMethodsFor:" : "",
		"realizeClass" : "BenjaminVanRyseghem 7/13/2012 16:13",
		"redoEnabled" : "",
		"redoLabel" : "",
		"redoOperation" : "",
		"refactoringOptions:" : "",
		"removeClassVarFrom:" : "",
		"removeClasses:" : "",
		"removeInstVarFrom:" : "",
		"removeMethodsFor:" : "",
		"removeParameterFor:" : "",
		"renameClass:" : "",
		"renameClassVarFrom:" : "",
		"renameClassVarNamed:from:" : "BenjaminVanRyseghem 4/18/2012 16:57",
		"renameInstVarFrom:" : "",
		"renameInstVarNamed:from:" : "BenjaminVanRyseghem 4/18/2012 16:55",
		"renameMethodFor:" : "",
		"renameTemporaryNamed:Between:from:" : "BenjaminVanRyseghem 6/26/2012 21:21",
		"renameTextSelection" : "BenjaminVanRyseghem 4/18/2012 16:47",
		"renameTextSelectionForClass" : "BenjaminVanRyseghem 4/18/2012 17:06",
		"renameTextSelectionForMethod" : "BenjaminVanRyseghem 4/18/2012 17:25",
		"renameVariable:" : "BenjaminVanRyseghem 4/18/2012 16:57",
		"request:" : "",
		"request:initialAnswer:" : "",
		"requestMethodNameFor:" : "",
		"requestSelfArgumentName" : "",
		"rewriteCode" : "",
		"rewriteCodeText" : "",
		"searchCode" : "",
		"searchCodeText" : "",
		"selectVariableToMoveMethodTo:class:" : "",
		"selectVariableTypesFrom:selected:for:" : "",
		"shouldExtractAssignmentTo:" : "BenjaminVanRyseghem 8/5/2012 21:51",
		"shouldOverride:in:" : "",
		"shouldUseExistingMethod:" : "StephaneDucasse 5/18/2012 14:54",
		"sourceRegex" : "",
		"sourceRegexText" : "",
		"splitCascadeBetween:from:" : "",
		"splitClass:" : "",
		"swapMethodFor:" : "",
		"temporaryToInstanceVariableNamed:Between:from:" : "",
		"typeClass" : "",
		"typeClassTextFor:" : "",
		"undoEnabled" : "",
		"undoLabel" : "",
		"undoOperation" : "" } }
