{
	"class" : {
		 },
	"instance" : {
		"checkUntypedVariablesOnly:" : "CamilloBruni 8/21/2012 16:30",
		"createContextFor:at:" : "",
		"testBlockTemporaries" : "",
		"testBlockTemporariesBoxed" : "",
		"testCompletionToken" : "",
		"testCompletionTokenEmpty" : "",
		"testCreateModel" : "",
		"testEmpty" : "",
		"testInTheMiddelOfAWord" : "",
		"testReceiverArgument" : "",
		"testReceiverCascade" : "",
		"testReceiverClassVar" : "",
		"testReceiverConstant" : "",
		"testReceiverGlobal" : "",
		"testReceiverGlobalVarNew" : "",
		"testReceiverTempVar" : "",
		"testReceiverTempVar2" : "",
		"testTemporaries" : "",
		"testUnfinishedString" : "",
		"testUntypedSelectorsOnly" : "",
		"testUntypedVarsOnly" : "" } }
