{
	"class" : {
		"category:source:" : "BenjaminVanRyseghem 2/27/2012 07:00" },
	"instance" : {
		"category" : "BenjaminVanRyseghem 2/27/2012 06:47",
		"category:" : "BenjaminVanRyseghem 2/27/2012 06:47",
		"generateSpec" : "BenjaminVanRyseghem 2/27/2012 07:50",
		"initialize" : "BenjaminVanRyseghem 2/27/2012 07:07",
		"selector" : "BenjaminVanRyseghem 2/27/2012 06:41",
		"selector:" : "BenjaminVanRyseghem 2/27/2012 06:41",
		"source" : "BenjaminVanRyseghem 2/27/2012 06:41",
		"source:" : "BenjaminVanRyseghem 2/27/2012 06:41" } }
