{
	"class" : {
		 },
	"instance" : {
		"accept" : "SvenVanCaekenberghe 12/13/2011 21:06",
		"close" : "SvenVanCaekenberghe 5/18/2011 11:49",
		"connect" : "SvenVanCaekenberghe 9/21/2011 13:48",
		"fillBytes:startingAt:count:" : "SvenVanCaekenberghe 12/9/2011 10:06",
		"flushBytes:startingAt:count:" : "SvenVanCaekenberghe 12/9/2011 09:37",
		"initialize" : "SvenVanCaekenberghe 5/18/2011 16:00",
		"initializeBuffers" : "SvenVanCaekenberghe 12/9/2011 12:47",
		"isConnected" : "SvenVanCaekenberghe 5/18/2011 11:49",
		"resetEncryptedBuffers" : "SvenVanCaekenberghe 5/18/2011 11:49",
		"sslException:code:" : "SvenVanCaekenberghe 5/18/2011 11:49",
		"sslSession" : "SvenVanCaekenberghe 9/13/2011 09:57",
		"sslSessionClass" : "SvenVanCaekenberghe 5/18/2011 11:51" } }
