{
	"class" : {
		"cleanUp" : "BenjaminVanRyseghem 3/16/2012 04:35",
		"ensureSingletonExistence" : "",
		"initialize" : "BenjaminVanRyseghem 3/16/2012 01:05",
		"new" : "",
		"open" : "BenjaminVanRyseghem 11/1/2011 07:38",
		"recentMessageListMenuOn:" : "BenjaminVanRyseghem 11/1/2011 07:51",
		"recentMessageListSettingOn:" : "BenjaminVanRyseghem 8/1/2012 15:03",
		"resetUniqueInstance" : "BenjaminVanRyseghem 3/16/2012 04:35",
		"startUp:" : "",
		"stopNotifications" : "GuillermoPolito 8/21/2012 19:12",
		"uniqueInstance" : "BenjaminVanRyseghem 3/16/2012 01:07" },
	"instance" : {
		"aClassHasBeenAdded:" : "",
		"aClassHasBeenCommented:" : "BenjaminVanRyseghem 3/16/2012 01:22",
		"aClassHasBeenModified:" : "",
		"aClassHasBeenRecategorized:" : "",
		"aClassHasBeenRemoved:" : "BenjaminVanRyseghem 11/29/2010 11:25",
		"aClassHasBeenRenamed:" : "StephaneDucasse 7/26/2011 14:22",
		"aClassHasBeenReorganized:" : "",
		"aMethodHasBeenAdded:" : "BenjaminVanRyseghem 11/29/2010 11:25",
		"aMethodHasBeenModified:" : "BenjaminVanRyseghem 3/16/2012 04:34",
		"aMethodHasBeenRecategorized:" : "",
		"aMethodHasBeenRemoved:" : "BenjaminVanRyseghem 11/29/2010 11:25",
		"addMethodReference:" : "BenjaminVanRyseghem 12/16/2010 15:53",
		"checkSize" : "BenjaminVanRyseghem 12/16/2010 15:57",
		"createAClassReference:" : "GuillermoPolito 8/3/2012 13:36",
		"createARemovalMethodReference:" : "GuillermoPolito 8/3/2012 13:36",
		"createTheMethodReference:" : "GuillermoPolito 8/21/2012 19:12",
		"defaultMaxListSize" : "BenjaminVanRyseghem 12/16/2010 15:52",
		"initialize" : "BenjaminVanRyseghem 3/16/2012 00:59",
		"maxListSize" : "BenjaminVanRyseghem 12/16/2010 15:52",
		"maxListSize:" : "BenjaminVanRyseghem 12/16/2010 15:55",
		"registerToAnnouncements" : "EstebanLorenzano 8/3/2012 14:20",
		"removeAClass:" : "GuillermoPolito 8/3/2012 13:37",
		"removeAMethod:" : "GuillermoPolito 8/3/2012 13:37",
		"stringMethodRemoved" : "StephaneDucasse 11/26/2010 17:03",
		"title" : "BenjaminVanRyseghem 1/11/2011 14:07" } }
