{
	"class" : {
		"browseChangeSetsWithClass:selector:" : "MarcusDenker 10/13/2012 18:09",
		"initialize" : "StephaneDucasse 9/9/2010 09:56",
		"open" : "IgorStasenko 2/19/2011 03:56",
		"patchworkUIThemeColor" : "AlainPlantec 12/16/2009 22:08",
		"registerToolsOn:" : "IgorStasenko 2/19/2011 03:02",
		"reorderChangeSets" : "StephaneDucasse 3/30/2010 23:04",
		"unload" : "AlainPlantec 10/17/2009 16:42" },
	"instance" : {
		"addPreamble" : "sd 11/20/2005 21:26",
		"addPriorVersionsCountForSelector:ofClass:to:" : "sw 2/22/2001 10:35",
		"browseChangeSet" : "BernardoContreras 1/18/2012 23:04",
		"browseMethodConflicts" : "BenjaminVanRyseghem 11/1/2011 07:41",
		"browseVersions" : "IgorStasenko 4/15/2011 17:07",
		"changeSet" : "tk 4/29/1998 08:22",
		"changeSetList" : "StephaneDucasse 3/29/2010 22:57",
		"changeSetListKey:from:" : "MarcusDenker 10/13/2012 16:01",
		"changeSetMenu:shifted:" : "MarcusDenker 10/13/2012 16:01",
		"changeSetName" : "BenjaminVanRyseghem 7/13/2012 15:31",
		"checkForAlienAuthorship" : "sw 10/30/2000 10:48",
		"checkForAnyAlienAuthorship" : "nk 3/30/2002 08:56",
		"checkForUnclassifiedMethods" : "sw 3/29/2001 12:47",
		"checkForUncommentedClasses" : "sw 7/18/2002 17:58",
		"checkForUncommentedMethods" : "sw 10/30/2000 10:39",
		"checkForUnsentMessages" : "sw 10/27/1999 14:20",
		"checkThatSidesDiffer:" : "sw 7/8/1999 13:36",
		"chooseChangeSet" : "StephaneDucasse 3/29/2010 16:09",
		"classList" : "sw 3/29/2001 15:19",
		"classListKey:from:" : "sw 3/5/2001 18:24",
		"classListMenu:shifted:" : "MarcusDenker 5/7/2012 15:12",
		"clearChangeSet" : "sd 11/20/2005 21:26",
		"contents:notifying:" : "StephaneDucasse 5/28/2011 13:32",
		"copyAllToOther" : "StephaneDucasse 2/4/2012 15:13",
		"copyClassToOther" : "sd 11/20/2005 21:26",
		"copyMethodToOther" : "sd 11/20/2005 21:26",
		"currentChangeSet" : "StephaneDucasse 2/13/2010 21:46",
		"currentClassName" : "BenjaminVanRyseghem 7/13/2012 15:30",
		"currentClassName:" : "BenjaminVanRyseghem 7/13/2012 15:31",
		"currentSelector" : "BenjaminVanRyseghem 7/13/2012 15:25",
		"currentSelector:" : "BenjaminVanRyseghem 7/13/2012 15:26",
		"editPostscript" : "tk 4/28/1998 08:06",
		"editPreamble" : "tk 4/28/1998 08:06",
		"fileIntoNewChangeSet" : "CamilloBruni 5/7/2012 02:09",
		"fileOut" : "tk 6/10/1999 12:44",
		"fileOutClass" : "StephaneDucasse 4/1/2010 09:48",
		"findChangeSet" : "StephaneDucasse 3/3/2010 13:45",
		"forget" : "sd 11/20/2005 21:26",
		"forgetClass" : "sd 11/20/2005 21:26",
		"inspectChangeSet" : "sw 1/10/1999 01:01",
		"label" : "tk 4/30/1998 13:37",
		"labelString" : "StephaneDucasse 3/29/2010 17:30",
		"lookForSlips" : "sw 2/17/1999 11:05",
		"mainButtonName" : "tk 4/24/1998 13:10",
		"messageList" : "sd 11/20/2005 21:26",
		"messageListKey:from:" : "sw 3/5/2001 18:30",
		"messageListMenu:shifted:" : "sw 3/9/2001 14:27",
		"messageMenu:shifted:" : "MarcusDenker 7/13/2012 23:52",
		"methodConflictsWithOtherSide" : "BenjaminVanRyseghem 11/1/2011 07:41",
		"modelWakeUp" : "sma 11/11/2000 23:28",
		"morphicWindow" : "StephaneDucasse 5/1/2011 17:22",
		"moveClassToOther" : "nb 6/17/2003 12:25",
		"moveMethodToOther" : "nk 7/30/2004 17:58",
		"myChangeSet:" : "sd 11/20/2005 21:26",
		"newCurrent" : "sd 5/23/2003 15:15",
		"newSet" : "StephaneDucasse 3/30/2010 22:45",
		"offerShiftedChangeSetMenu" : "sw 2/27/2001 21:55",
		"offerUnshiftedChangeSetMenu" : "sw 3/6/2001 14:41",
		"open" : "alain.plantec 5/30/2008 11:08",
		"openAsMorph" : "JuanVuletich 10/21/2010 17:07",
		"openAsMorphIn:rect:" : "BenjaminVanRyseghem 7/13/2012 15:32",
		"parent" : "tk 4/24/1998 08:42",
		"parent:" : "sd 11/20/2005 21:26",
		"promoteToTopChangeSet" : "StephaneDucasse 3/29/2010 15:50",
		"remove" : "di 6/14/1998 12:00",
		"removeContainedInClassCategories" : "StephaneDucasse 3/29/2010 17:35",
		"removeMessage" : "StephaneDucasse 5/28/2011 13:44",
		"removePostscript" : "sw 6/29/1999 20:53",
		"removePreamble" : "sw 3/5/1999 19:32",
		"removePrompting:" : "StephaneDucasse 3/23/2010 22:33",
		"rename" : "StephaneDucasse 3/29/2010 16:09",
		"reorderChangeSets" : "StephaneDucasse 3/31/2010 16:41",
		"selectedClass" : "sd 11/20/2005 21:26",
		"selectedClassOrMetaClass" : "lr 3/14/2010 21:13",
		"selectedMessageName" : "jm 5/4/1998 07:32",
		"setContents" : "PeterHugossonMiller 9/3/2009 00:52",
		"shiftedChangeSetMenu:" : "StephaneDucasse 3/29/2010 22:58",
		"shiftedMessageMenu:" : "MarcusDenker 10/13/2012 18:05",
		"showChangeSet:" : "StephaneDucasse 2/4/2012 15:21",
		"showChangeSetNamed:" : "BenjaminVanRyseghem 7/13/2012 15:31",
		"submergeIntoOtherSide" : "sd 11/20/2005 21:26",
		"subtractOtherSide" : "sw 7/8/1999 12:32",
		"toggleDiffing" : "sw 11/13/2001 07:34",
		"trimHistory" : "di 5/12/2000 15:03",
		"update" : "di 6/21/1998 13:02",
		"updateIfNecessary" : "StephaneDucasse 3/30/2010 22:51",
		"veryDeepFixupWith:" : "sd 11/20/2005 21:26",
		"veryDeepInner:" : "sd 11/20/2005 21:26",
		"wantsOptionalButtons" : "JW 2/2/2001 21:41" } }
