{
	"class" : {
		"selector:arguments:body:" : "",
		"selector:body:" : "",
		"selectorParts:arguments:" : "" },
	"instance" : {
		"=" : "lr 10/18/2009 16:03",
		"accept:" : "CamilloBruni 2/3/2012 15:53",
		"acceptVisitor:" : "",
		"addNode:" : "lr 1/4/2012 21:40",
		"addReplacement:" : "",
		"addReturn" : "lr 1/4/2012 21:38",
		"addSelfReturn" : "lr 1/4/2012 21:38",
		"allArgumentVariables" : "",
		"allDefinedVariables" : "",
		"argumentNames" : "",
		"arguments" : "",
		"arguments:" : "",
		"body" : "",
		"body:" : "",
		"buildSelector" : "",
		"changeSourceSelectors:arguments:" : "lr 2/21/2010 13:51",
		"children" : "lr 11/1/2009 19:57",
		"clearReplacements" : "",
		"copyInContext:" : "lr 5/30/2010 12:26",
		"defines:" : "",
		"equalTo:withMapping:" : "lr 10/18/2009 15:44",
		"hasPragmaNamed:" : "CamilloBruni 2/3/2012 15:47",
		"hash" : "lr 3/7/2010 13:55",
		"initialize" : "",
		"isLast:" : "",
		"isMethod" : "",
		"isPrimitive" : "lr 11/1/2009 19:37",
		"lastIsReturn" : "",
		"map:to:" : "",
		"mappingFor:" : "",
		"match:inContext:" : "lr 5/30/2010 12:22",
		"matchPragmas:against:inContext:" : "lr 5/30/2010 12:23",
		"methodComments" : "",
		"methodNode" : "",
		"newSource" : "",
		"numArgs" : "",
		"postCopy" : "lr 11/24/2009 23:22",
		"pragmas" : "lr 11/1/2009 19:34",
		"pragmas:" : "lr 11/1/2009 19:34",
		"primitiveSources" : "TestRunner 11/5/2009 11:48",
		"printOn:" : "",
		"references:" : "",
		"reformatSource" : "TestRunner 12/23/2009 21:13",
		"renameSelector:andArguments:" : "",
		"replaceNode:withNode:" : "",
		"selector" : "",
		"selector:" : "lr 8/8/2010 13:15",
		"selectorParts" : "",
		"selectorParts:" : "",
		"selectorParts:arguments:" : "",
		"source" : "",
		"source:" : "",
		"start" : "",
		"statements" : "CamilloBruni 2/3/2012 16:42",
		"stop" : "",
		"temporaries" : "CamilloBruni 2/3/2012 16:41",
		"temporaryNames" : "CamilloBruni 12/8/2011 16:19",
		"uses:" : "" } }
