{
	"class" : {
		 },
	"instance" : {
		"accessValuePutIn" : "stephane.ducasse 10/5/2008 13:06",
		"accessValuePutInOn:" : "stephane.ducasse 10/5/2008 13:06",
		"empty" : "AlexandreBergel 1/19/2009 18:12",
		"nonEmpty" : "AlexandreBergel 1/19/2009 18:12",
		"selectorToAccessValuePutIn" : "stephane.ducasse 10/5/2008 13:05",
		"test0FixtureEmptySequenceableTest" : "delaunay 5/12/2009 14:57",
		"testSequenceAbleIfEmptyifNotEmptyDo" : "stephane.ducasse 10/5/2008 12:57",
		"testSequenceIfEmptyifNotEmptyDo" : "stephane.ducasse 10/5/2008 12:59",
		"testSequenceIfNotEmpty" : "stephane.ducasse 10/5/2008 13:02",
		"testSequenceIfNotEmptyDo" : "stephane.ducasse 10/5/2008 13:03",
		"testSequenceIfNotEmptyDoifNotEmpty" : "stephane.ducasse 10/5/2008 13:04",
		"testSequenceIfNotEmptyifEmpty" : "stephane.ducasse 10/5/2008 13:05",
		"valuePutIn" : "stephane.ducasse 10/5/2008 13:06" } }
