{
	"class" : {
		 },
	"instance" : {
		">>" : "al 8/2/2004 16:26",
		"addExclusionOf:to:" : "al 7/30/2004 21:51",
		"addSelector:withMethod:" : "al 7/30/2004 22:43",
		"addSelector:withMethod:notifying:" : "al 7/30/2004 22:43",
		"addSelectorSilently:withMethod:" : "al 9/16/2005 14:31",
		"addToComposition:" : "al 1/9/2006 17:58",
		"addTraitSelector:withMethod:" : "CamilloBruni 4/27/2012 18:22",
		"allSelectors" : "al 9/16/2005 14:12",
		"applyChangesOfNewTraitCompositionReplacing:" : "al 7/30/2004 21:39",
		"basicAddSelector:withMethod:" : "MarcusDenker 2/26/2012 12:52",
		"basicLocalSelectors" : "al 9/16/2005 14:13",
		"basicLocalSelectors:" : "al 9/16/2005 14:13",
		"basicRemoveSelector:" : "MarcusDenker 2/26/2012 12:53",
		"canUnderstand:" : "al 9/16/2005 14:16",
		"canZapMethodDictionary" : "al 9/16/2005 14:23",
		"changeRecordsAt:" : "al 11/28/2005 21:48",
		"classAndMethodFor:do:ifAbsent:" : "al 9/16/2005 14:14",
		"compiledMethodAt:" : "al 8/2/2004 16:29",
		"compiledMethodAt:ifAbsent:" : "al 7/30/2004 20:55",
		"compress" : "al 7/30/2004 20:55",
		"copyOfMethodDictionary" : "al 7/30/2004 22:51",
		"deepCopy" : "al 9/16/2005 14:20",
		"deregisterLocalSelector:" : "al 11/28/2005 11:46",
		"emptyMethodDictionary" : "al 12/1/2005 16:01",
		"ensureLocalSelectors" : "nice 12/4/2009 00:06",
		"environment" : "StephaneDucasse 3/20/2010 17:24",
		"firstCommentAt:" : "al 12/1/2005 15:40",
		"firstPrecodeCommentFor:" : "PeterHugossonMiller 9/2/2009 16:00",
		"flattenDown:" : "jannik.laval 5/1/2010 16:32",
		"flattenDownAllTraits" : "jannik.laval 5/1/2010 16:32",
		"formalHeaderPartsFor:" : "al 9/16/2005 14:49",
		"formalParametersAt:" : "nice 12/25/2009 20:54",
		"hasMethods" : "marcus.denker 8/25/2008 09:23",
		"hasTraitComposition" : "al 9/16/2005 14:29",
		"includesBehavior:" : "al 3/1/2006 23:02",
		"includesLocalSelector:" : "al 9/16/2005 14:16",
		"includesSelector:" : "al 7/30/2004 22:35",
		"isAliasSelector:" : "StephaneDucasse 4/27/2010 11:54",
		"isDisabledSelector:" : "al 9/16/2005 14:16",
		"isLocalAliasSelector:" : "StephaneDucasse 4/27/2010 11:55",
		"literalScannedAs:notifying:" : "marcus.denker 11/10/2008 10:04",
		"localSelectors" : "nice 12/4/2009 00:07",
		"longPrintOn:" : "al 9/16/2005 14:21",
		"lookupSelector:" : "al 9/16/2005 14:50",
		"methodDict" : "al 9/16/2005 14:50",
		"methodDict:" : "al 9/16/2005 14:50",
		"methodDictAddSelectorSilently:withMethod:" : "adrian_lienhard 2/17/2009 22:00",
		"methodDictionary" : "al 7/30/2004 21:02",
		"methodDictionary:" : "al 9/30/2005 18:24",
		"methodHeaderFor:" : "al 9/16/2005 14:50",
		"methodsDo:" : "al 7/30/2004 21:02",
		"name" : "al 9/16/2005 14:21",
		"noteChangedSelectors:" : "al 8/6/2004 13:09",
		"notifyUsersOfChangedSelector:" : "al 7/30/2004 21:40",
		"notifyUsersOfChangedSelectors:" : "al 7/30/2004 21:40",
		"obsolete" : "al 12/1/2005 15:24",
		"postCopy" : "nice 1/13/2010 21:59",
		"prettyPrinterClass" : "damiencassou 7/30/2009 11:07",
		"purgeLocalSelectors" : "al 11/28/2005 11:47",
		"registerLocalSelector:" : "al 11/28/2005 11:47",
		"removeAlias:of:" : "al 7/30/2004 21:54",
		"removeFromComposition:" : "al 10/22/2006 18:22",
		"removeSelector:" : "StephaneDucasse 4/27/2010 11:55",
		"removeSelectorSilently:" : "EstebanLorenzano 8/3/2012 15:29",
		"removeTraitSelector:" : "jannik.laval 5/1/2010 16:32",
		"selectors" : "al 7/30/2004 21:03",
		"selectorsAndMethodsDo:" : "nice 1/16/2010 12:50",
		"selectorsDo:" : "al 7/30/2004 21:03",
		"selectorsWithArgs:" : "nice 1/5/2010 15:59",
		"setTraitComposition:" : "al 7/30/2004 21:48",
		"setTraitCompositionFrom:" : "apb 8/22/2005 18:28",
		"sourceCodeAt:" : "MarcusDenker 4/26/2012 14:15",
		"sourceCodeAt:ifAbsent:" : "MarcusDenker 4/26/2012 14:15",
		"spaceUsed" : "nice 1/16/2010 12:52",
		"standardMethodHeaderFor:" : "al 9/16/2005 14:51",
		"storeLiteral:on:" : "al 12/1/2005 15:37",
		"thoroughHasSelectorReferringTo:special:byte:" : "HenrikSperreJohansen 2/5/2010 14:06",
		"thoroughWhichSelectorsReferTo:special:byte:" : "marcus.denker 9/29/2008 08:46",
		"traitComposition" : "al 9/16/2005 14:30",
		"traitComposition:" : "al 9/16/2005 14:53",
		"traitCompositionIncludes:" : "al 9/16/2005 14:31",
		"traitCompositionString" : "al 3/26/2006 21:29",
		"traitOrClassOfSelector:" : "al 7/30/2004 21:55",
		"traitTransformations" : "al 9/16/2005 14:53",
		"traits" : "damiencassou 1/6/2009 10:58",
		"traitsProvidingSelector:" : "MarianoMartinezPeck 6/26/2012 10:40",
		"ultimateSourceCodeAt:ifAbsent:" : "al 9/16/2005 14:51",
		"updateMethodDictionarySelector:" : "GuillermoPolito 7/7/2012 14:34",
		"whichSelectorsReferTo:" : "StephaneDucasse 3/20/2010 22:05",
		"whichSelectorsReferTo:special:byte:" : "md 2/15/2006 11:01",
		"withAllSubclassesDo:" : "damiencassou 1/20/2009 10:35",
		"withAllSuperclasses" : "al 12/31/2005 13:40" } }
