{
	"class" : {
		"example1" : "mk 8/14/2005 16:07" },
	"instance" : {
		"adjustAfter:" : "stephane.ducasse 10/16/2008 17:27",
		"asFlexOf:" : "di 2/21/98 14:35",
		"chooseSmoothing" : "aoy 2/17/2003 01:02",
		"computeBounds" : "ar 11/21/2000 17:00",
		"degreesOfFlex" : "AlainPlantec 5/7/2010 23:39",
		"drawOn:" : "di 2/23/98 19:59",
		"extent:" : "nice 1/5/2010 15:59",
		"forwardDirection" : "AlainPlantec 5/7/2010 23:52",
		"grabTransform" : "ar 10/22/2000 18:26",
		"hasNoScaleOrRotation" : "jm 4/25/1998 05:55",
		"heading" : "AlainPlantec 5/7/2010 23:35",
		"isFlexMorph" : "jm 4/17/1998 00:44",
		"isRenderer" : "jm 5/7/1998 13:46",
		"isSticky" : "marcus.denker 9/17/2008 19:13",
		"layoutChanged" : "ar 10/25/2000 16:21",
		"prepareForRotating" : "AlainPlantec 5/7/2010 21:29",
		"prepareForScaling" : "AlainPlantec 5/7/2010 21:29",
		"printOn:" : "dgd 2/21/2003 22:42",
		"referencePosition" : "sw 3/28/2001 14:24",
		"removeFlexShell" : "stephane.ducasse 11/8/2008 19:33",
		"renderedMorph" : "AlainPlantec 5/7/2010 22:02",
		"replaceSubmorph:by:" : "di 11/18/1999 15:44",
		"rotationDegrees" : "AlainPlantec 5/7/2010 23:00",
		"rotationDegrees:" : "AlainPlantec 5/8/2010 00:04",
		"scaleFactor" : "sw 2/15/2002 02:27",
		"scaleToMatch:" : "ar 9/23/2000 13:40",
		"setDirectionFrom:" : "AlainPlantec 5/7/2010 23:56",
		"stepTime" : "mdr 10/3/2000 11:28",
		"transformedBy:" : "ar 10/25/2000 16:24",
		"visible:" : "sw 10/6/2004 11:33" } }
